trexadmin
