Metadata-Version: 2.4
Name: trex_admin
Version: 1.0.3
Summary: TRex admin package
Author: Jack Lok
Requires-Dist: flask
Requires-Dist: Jinja2
Requires-Dist: MarkupSafe
Requires-Dist: phonenumbers
Requires-Dist: requests
Requires-Dist: testfixtures
Requires-Dist: flask-babel
Requires-Dist: Flask-CORS
Requires-Dist: trex-lib
Requires-Dist: trex-model
Requires-Dist: trex-mail
Dynamic: author
Dynamic: requires-dist
Dynamic: summary
